lexi/__init__.py
lexi/document_importers/__init__.py
lexi/document_importers/confluence_importer.py
lexi/document_importers/document_importer_interface.py
lexi/document_importers/other_importer.py
lexi/document_processors/__init__.py
lexi/document_processors/document_processor_interface.py
lexi/document_processors/simple_document_processor.py
lexi/main.py
lexi/settings.py
lexi/system/docker-compose.yml
lexi/system/envrc_template.txt
lexi/system/litellm/litellm-config.yaml
lexi/system/nginx/default.conf
lexi/system/nginx/index.html
lexi/system/verba/Dockerfile
lexi/tui/__init__.py
lexi/tui/schema.py
lexi/tui/system.py
lexi/utils/__init__.py
lexi/utils/rich_logger.py
lexi/verba_interface/__init__.py
lexi/verba_interface/chunk.py
lexi/verba_interface/chunker.py
lexi/verba_interface/document.py
lexi-0.1.1.dist-info/METADATA
lexi-0.1.1.dist-info/WHEEL
lexi-0.1.1.dist-info/entry_points.txt
lexi-0.1.1.dist-info/RECORD
