Metadata-Version: 2.1
Name: lexi
Version: 0.1.1
Summary: Lexi is a local LLM-based solution - includes Chat UI, RAG, LLM Proxy, and Document importing
License: MIT
Author: Matthew Thompson
Author-email: thompsonson@gmail.com
Requires-Python: >=3.10,<4.0
Classifier: License :: OSI Approved :: MIT License
Classifier: Programming Language :: Python :: 3
Classifier: Programming Language :: Python :: 3.10
Classifier: Programming Language :: Python :: 3.11
Classifier: Programming Language :: Python :: 3.12
Requires-Dist: atlassian-python-api (>=3.41.11,<4.0.0)
Requires-Dist: beautifulsoup4 (>=4.12.3,<5.0.0)
Requires-Dist: langchain (>=0.1.10,<0.2.0)
Requires-Dist: langchain-community (>=0.0.25,<0.0.26)
Requires-Dist: lxml (>=5.1.0,<6.0.0)
Requires-Dist: pillow (>=10.2.0,<11.0.0)
Requires-Dist: rich (>=13.7.1,<14.0.0)
Requires-Dist: tiktoken (>=0.6.0,<0.7.0)
Requires-Dist: tqdm (>=4.66.2,<5.0.0)
Requires-Dist: typer (>=0.9.0,<0.10.0)
Requires-Dist: wasabi (>=1.1.2,<2.0.0)
Requires-Dist: weaviate-client (>=4.5.0,<5.0.0)
